{"id":127,"name":"Sky Habitat","website":"https://www.skyhabitat.sg/","year":2015,"address":null,"gfa":"65000","gmapsEmbed":"!1m18!1m12!1m3!1d3988.7070380681225!2d103.84962181479635!3d1.3523320619440682!2m3!1f0!2f0!3f0!3m2!1i1024!2i768!4f13.1!3m3!1m2!1s0x31da1710d8b2f855%3A0x3c0b50a1af4f8db2!2sSky%20Habitat!5e0!3m2!1sen!2sbr!4v1573672432487!5m2!1sen!2sbr","gmapsLink":"https://goo.gl/maps/afwtq9WLdjUosQEz9","height":"130","lat":null,"lng":null,"typology":"Residential","architectBuildings":{"totalCount":1,"nodes":[{"architect":{"id":83,"name":"Safdie Architects","website":"https://www.safdiearchitects.com/"}}]},"city":{"country":{"id":6,"iso":"SG","name":"Singapore"},"id":8,"name":"Singapore"},"links":{"totalCount":4,"nodes":[{"id":392,"title":"Sky Habitat Singapore / Safdie Architects ","url":"https://www.archdaily.com/781936/sky-habitat-singapore-moshe-safdie","source":{"id":1,"name":"ArchDaily","website":"http://www.archdaily.com"}},{"id":393,"title":"Moshe Safdie completes Singapore Sky Habitat featuring aerial \"streets\" and gardens","url":"https://www.dezeen.com/2016/02/09/sky-habitat-moshe-safdie-architects-singapore-housing/","source":{"id":2,"name":"Dezeen","website":"https://www.dezeen.com"}},{"id":394,"title":"Moshe Safdie's completed sky habitat features landscaped bridges","url":"https://www.designboom.com/architecture/moshe-safdie-sky-habitat-singapore-bishan-residential-development-02-03-2016/","source":{"id":9,"name":"designboom","website":"http://www.designboom.com/"}},{"id":395,"title":"Moshe Safdie on Sky Habitat","url":"https://www.indesignlive.sg/articles/cubes/moshe-safdie-on-sky-habitat","source":{"id":14,"name":"INDESIGNLIVE.sg","website":"https://www.indesignlive.sg/"}}]}}