{"id":81,"name":"Sony Center","website":"http://www.sonycenter.de/en","year":2000,"address":"","gfa":"132000","gmapsEmbed":"!1m18!1m12!1m3!1d2428.3034334803115!2d13.371313815984823!3d52.509847544733724!2m3!1f0!2f0!3f0!3m2!1i1024!2i768!4f13.1!3m3!1m2!1s0x47a851c998132f33%3A0x70a22ab9734c6bdb!2sSony+Center%2C+10785+Berlin!5e0!3m2!1sen!2sde!4v1506333199287","gmapsLink":"https://goo.gl/maps/qx3uU3taLrt","height":"103","lat":52.5098,"lng":13.3713,"typology":"Office, residential, entertainment","architectBuildings":{"totalCount":1,"nodes":[{"architect":{"id":65,"name":"JAHN","website":"http://www.jahn-us.com/"}}]},"city":{"country":{"id":5,"iso":"DE","name":"Germany"},"id":7,"name":"Berlin"},"links":{"totalCount":4,"nodes":[{"id":281,"title":"Archdaily","url":"http://www.archdaily.com/173305/flashback-sony-center-berlin-murphy-jahn%5D(http://www.archdaily.com/173305/flashback-sony-center-berlin-murphy-jahn","source":{"id":1,"name":"ArchDaily","website":"http://www.archdaily.com"}},{"id":282,"title":"ARUP project page","url":"https://www.arup.com/projects/sony-centre","source":null},{"id":283,"title":"Wikiarquitectura","url":"https://en.wikiarquitectura.com/building/sony-center/%5D(https://en.wikiarquitectura.com/building/sony-center/","source":{"id":12,"name":"Wikiarquitectura","website":"https://en.wikiarquitectura.com/"}},{"id":284,"title":"The Skyscraper Center","url":"https://www.skyscrapercenter.com/building/bahn-tower/10083%5D(https://www.skyscrapercenter.com/building/bahn-tower/10083","source":{"id":11,"name":"The Skyscraper Center","website":"https://www.skyscrapercenter.com/"}}]}}